lightdash_ops/__init__.py
lightdash_ops/utils.py
lightdash_ops/cli/__init__.py
lightdash_ops/cli/exposures.py
lightdash_ops/cli/main.py
lightdash_ops/cli/organization_v1.py
lightdash_ops/cli/project.py
lightdash_ops/lightdash/__init__.py
lightdash_ops/lightdash/settings.py
lightdash_ops/lightdash/models/__init__.py
lightdash_ops/lightdash/models/base_user.py
lightdash_ops/lightdash/models/exposure.py
lightdash_ops/lightdash/models/organization.py
lightdash_ops/lightdash/models/project.py
lightdash_ops/lightdash/models/project_member.py
lightdash_ops/lightdash/models/space.py
lightdash_ops/lightdash/models/user_group.py
lightdash_ops/lightdash/services/__init__.py
lightdash_ops/lightdash/services/get_organization_members.py
lightdash_ops/lightdash/v1/__init__.py
lightdash_ops/lightdash/v1/client.py
lightdash_ops/lightdash/v1/create_space_in_project.py
lightdash_ops/lightdash/v1/get_authenticated_user.py
lightdash_ops/lightdash/v1/get_dbt_exposures.py
lightdash_ops/lightdash/v1/get_explore.py
lightdash_ops/lightdash/v1/get_explores.py
lightdash_ops/lightdash/v1/get_my_organization.py
lightdash_ops/lightdash/v1/get_organization_member_by_uuid.py
lightdash_ops/lightdash/v1/get_project.py
lightdash_ops/lightdash/v1/get_project.py.py
lightdash_ops/lightdash/v1/get_space.py
lightdash_ops/lightdash/v1/list_groups_in_organization.py
lightdash_ops/lightdash/v1/list_organization_members.py
lightdash_ops/lightdash/v1/list_organization_projects.py
lightdash_ops/lightdash/v1/list_spaces_in_project.py
lightdash_ops/lightdash/v1/organization/get_organization.py
lightdash_ops/operators/__init__.py
lightdash_ops/operators/exposures_v1.py
lightdash_ops/operators/organization_v1.py
lightdash_ops/operators/project_v1.py
lightdash_ops/tests/__init__.py
lightdash_ops/tests/utils.py
lightdash_ops/tests/lightdash/__init__.py
lightdash_ops/tests/lightdash/test_settings.py
lightdash_ops/tests/lightdash/api/test_get_authenticated_user.py
lightdash_ops-0.3.1.dist-info/entry_points.txt
lightdash_ops-0.3.1.dist-info/LICENSE
lightdash_ops-0.3.1.dist-info/WHEEL
lightdash_ops-0.3.1.dist-info/METADATA
lightdash_ops-0.3.1.dist-info/RECORD
