Metadata-Version: 2.1
Name: lightdash-ops
Version: 0.3.1
Summary: The CLI enables us to operate resources on Lightdash.
Author: yu-iskw
Requires-Python: >=3.9.0
Classifier: Development Status :: 4 - Beta
Classifier: Intended Audience :: Information Technology
Classifier: Intended Audience :: System Administrators
Classifier: Operating System :: OS Independent
Classifier: Topic :: Software Development :: Libraries
Classifier: Topic :: Software Development :: Libraries :: Python Modules
Classifier: License :: OSI Approved :: Apache Software License
Classifier: Programming Language :: Python
Classifier: Programming Language :: Python :: 3
Classifier: Programming Language :: Python :: 3 :: Only
Classifier: Programming Language :: Python :: 3.9
Classifier: Programming Language :: Python :: 3.10
Classifier: Programming Language :: Python :: 3.11
Classifier: Programming Language :: Python :: 3.12
Classifier: Typing :: Typed
Requires-Dist: pydantic[dotenv] >=2.7,<3.0
Requires-Dist: pydantic-settings >=2.0,<3.0
Requires-Dist: requests >=2.28.0,<3.0
Requires-Dist: loguru >=0.7.0,<1.0.0
Requires-Dist: click >=8.0,<9.0
Requires-Dist: email-validator>=2.0,<3.0
Requires-Dist: ruamel.yaml >=0.17,<0.18
Requires-Dist: flit ==3.7.1 ; extra == "dev"
Requires-Dist: build ==0.7.0 ; extra == "dev"
Requires-Dist: yapf >=0.29.0 ; extra == "dev"
Requires-Dist: pyyaml >=5.3 ; extra == "dev"
Requires-Dist: yamllint >=1.35.1,<2.0.0 ; extra == "dev"
Requires-Dist: types-PyYAML >=6.0,<7.0 ; extra == "dev"
Requires-Dist: pdoc3 >=0.9.2 ; extra == "dev"
Requires-Dist: pre-commit >=2.15.0 ; extra == "dev"
Requires-Dist: safety >=2.0,<3.0 ; extra == "dev"
Requires-Dist: pytest >=7.0.0,<8.0.0 ; extra == "test"
Requires-Dist: py >=1.11.0,<2.0.0 ; extra == "test"
Requires-Dist: parameterized >=0.7.0, <1.0.0 ; extra == "test"
Requires-Dist: pylint >=2.12.0 ; extra == "test"
Requires-Dist: mypy >=1.3.0,<2.0.0 ; extra == "test"
Requires-Dist: flake8 >=3.8.3,<4.0.0 ; extra == "test"
Requires-Dist: black ==21.9b0 ; extra == "test"
Requires-Dist: isort >=5.0.6,<6.0.0 ; extra == "test"
Requires-Dist: yapf >=0.29.0 ; extra == "test"
Project-URL: Home, https://github.com/yu-iskw/lightdash-ops
Provides-Extra: dev
Provides-Extra: doc
Provides-Extra: test
